eta_connect/__init__.py
eta_connect/connectors/__init__.py
eta_connect/connectors/base_classes.py
eta_connect/connectors/common.py
eta_connect/connectors/cumulocity.py
eta_connect/connectors/emonio.py
eta_connect/connectors/eneffco.py
eta_connect/connectors/entso_e.py
eta_connect/connectors/forecast_solar.py
eta_connect/connectors/live_connect.py
eta_connect/connectors/modbus.py
eta_connect/connectors/node.py
eta_connect/connectors/opc_ua.py
eta_connect/connectors/sub_handlers.py
eta_connect/connectors/util.py
eta_connect/connectors/wetterdienst_connection.py
eta_connect/py.typed
eta_connect/servers/__init__.py
eta_connect/servers/modbus.py
eta_connect/servers/opc_ua.py
eta_connect/timeseries/__init__.py
eta_connect/timeseries/dataframes.py
eta_connect/timeseries/scenarios.py
eta_connect/type_hints/__init__.py
eta_connect/type_hints/custom_types.py
eta_connect/type_hints/types_connectors.py
eta_connect/util.py
examples/__init__.py
examples/connectors/__init__.py
examples/connectors/cumulocity_examples.py
examples/connectors/read_emonio_live.py
examples/connectors/read_series_eneffco.py
examples/connectors/read_series_entsoe.py
examples/connectors/read_series_forecast_solar.py
examples/connectors/read_series_wetterdienst.py
examples/forecasting/__init__.py
examples/forecasting/main.py
examples/forecasting/resources/emag_gt_forecast.onnx
eta_connect-0.1.0.dist-info/LICENSE
eta_connect-0.1.0.dist-info/METADATA
eta_connect-0.1.0.dist-info/WHEEL
eta_connect-0.1.0.dist-info/RECORD
